{
  "name": "Ellen Hoffman",
  "age": 65,
  "address": {
    "street": "Simloj Loop",
    "city": "Doepiceh",
    "state": "OR",
    "zip": "31948"
  },
  "contact": {
    "phone": "(302) 548-4059",
    "servicePhone": "800592287"
  },
  "birthday": "1967-06-15T02:36:01.785Z",
  "ip": "16.220.17.100",
  "foo": "bar",
  "profile": {
    "about": "Mih nevtijnu incusas guisi biwdizsa epete olomajme pezbik sobod lerastif luzukfev zazmuhu fuat nesa kiab gi. Uw bul wolzifna esiku zasutic alfufa bufar bohiobu miizero lu du rerge bura. Iji naw ev bo rek kozbatgan gavilrap uk jik to lutuce kin nel roewalu tenova ulcavde.",
    "bio": "Jojulorer pooz zedzuuco da ur uwuzogo tuzaw rugalew sokov vo olodofa duwofipa ilafasob. Wiocinu hubtefa luhta nufwer fu samoheg zevektu lajaeza jek wil setwu okemuwu luucagow bugzuwzo rerekin medas faw corowesez. Ko sizso atosofi pah gen hap nublo pawicsuv lezmuc pozjova nic afwe aw oj butsud nuk janilbu. Nohwo lohleb bi toujo demuk nijsu muog icsa ni pehihuba ire acjak alian jufivoam nu. Eno heju le kojuhdol udisiw gif ok ocziefi jev za girzuvi lerep ajisce. La udufo mutotra zohhahef ihmitfe irupe hewla ojiahaji tekcu rawepak dev kisiw buzewoh tinsonen camo dawav. He upioca mos ebga ijahubu de vocorven fet jotonovu pum owawemni uj op jihijvap."
  },
  "apiKey": "862bfaf6f6625bf23e5f15fa982584f57e0f1a657f08e88db0f0f21e19289f83",
  "currency": {
    "code": "CNY",
    "name": "China Yuan Renminbi"
  }
}