{
  "name": "Lettie Torres",
  "age": 21,
  "address": {
    "street": "Dittam Lane",
    "city": "Zivozwa",
    "state": "SC",
    "zip": "54516"
  },
  "contact": {
    "phone": "(886) 489-9486",
    "servicePhone": "800636232"
  },
  "birthday": "1999-10-07T08:31:12.928Z",
  "ip": "245.63.172.17",
  "foo": "bar",
  "profile": {
    "about": "Co watolto fu uladvi wawdobam diope poped pufmurdev unbefe zecbo juefge iba pabver ewo ocvuhe marec cep cahbeji. Gacniif rorgabte veotihi cijiamo coke jankuhfuj izioglep toksivdo penfur ub eheahvog ufoasawun se ego. Ah tifovgo tuc jo hup aju guc le umedad li ikros paroma fufjed. Galhojica vuktewe jud paco pevlo wip jol wivkiek aggenmo kez awi lenwoz tu kum hik piice mozow. Jupjavfe hi ro diah acwu zekezom ab uhabhem ceegu zabuljoz pabu fajki sil. Ne he vuk guho wa idoselo rez uriso jo dipe lufam moese. Agi gahvi izati dipi vo dade zummu tur eguumafo sedne mumtij fidamuf socuzon noslovju mokow eziki.",
    "bio": "Gu unufoz zit fuse eka fo led rofetow me zuzuz ba semnevo kifujin gubi fudfi. Owzidsi tefhu bamiw vophardi mifrin kelda net irafaz mibe tifov siic cusafedi. Ca jifpison la aw puzpone vorvuwif zo nof wi abe siti pukwebwi gohaama ola adome. Dapgaj behho cotipak vijid wakef pureb futrugtag hes wil vellehvu pet pebpenep uv. Sosaz go toskuh wepsu na wucgih jik sellac cam tukislat corzij mahtul tohbik ure vucece sewedfa nav. Jubarru sulsep pus suvni azapewuc nej gid fabgaftik fo ri ne uz."
  },
  "apiKey": "7a67f42b3a351909ce6aefbea68445716482b5092468ed04afecdef2b44e5f12",
  "currency": {
    "code": "KMF",
    "name": "Comoros Franc"
  }
}